<?xml version="1.0" standalone="yes"?>
<content>
    <header level="1" type="parsha" name="bereshit" >
        <header level="2" type="chapter" name='17'>
            <header level="2" type="letter" name='4'>
                <fragment></fragment>
                <header type='ref' name="eeviru_lifney_odom">
                    <header type='girsa' name='main'>
                        <p>Провёл их перед человеком.Сказал ему: "Эти - как их назвать?"</p>
                        <p>Сказал: "Это - бык, это - осёл, это - лошадь, это - верблюд"</p>
                        <p>"А ты - как твоё имя?"</p>
                        <p>Сказал Ему: "Мне подобает называться Адам, потому что я сотворён из земли (адама)"</p>
                        <p>А Я, какое Моё Имя?</p>
                        <work_needed><p>Сказал Ему: "Тебе подобает называться Г-сподь, потому что ты господин над всем Своим творением."</p>
                        <p>Сказал Раби Аха: (Ишаяу 42): "Я Авайе, это моё Имя" - это Моё Имя, которым назвал меня Адам аришон.</p></work_needed>
                    </header>
                    <header type='girsa' name='joseph_isaac_schneersohn_sefer_hamaamarim_5682_0004'>
                        <p>Провёл их перед человеком.Сказал ему: "Эти - как их назвать?"</p>
                        <p>Сказал: "Это - бык, это - осёл"</p>
                        <p>"А ты - как твоё имя?"</p>
                        <p>Сказал Ему: "Мне подобает называться Адам, потому что я сотворён из земли (адама)"</p>
                        <p>А Я, какое Моё Имя?</p>
                        <work_needed><p>Сказал Ему: "Тебе подобает называться Авайе, потому что ты господин над всем Своим творением."</p></work_needed>
                        <p>Сказал Раби Аха: (Ишаяу 42): "Я Авайе, это моё Имя" - это Моё Имя, которым назвал меня Адам аришон.</p>
                    </header>
                </header>
                <fragment></fragment>
            </header>
        </header>
    </header>
</content>