<?xml version="1.0" standalone="yes"?>
<content>
    <header type="chapter" level='0' name="7" >
        <header type='mishna' level='1' name='5'>
			<p>Гид аноше сварили с другими жилами. Если его можно идентифицировать - надо чтобы не чувствовался его вкус. Если нет - всё запрещено. Жидкость [будет разрешена] если не чувствуется его вкус.</p>
			<p>И так же кусок невейлы или некашерной рыбы: если их сварили с разрешённой едой и их можно идентифицировать - [еда будет разрешена] если не чувствуется вкус [запрета]. Если [запрет] не [идентифицируемый] - всё запрещено. Жидкость [будет разрешена] если не чувствуется вкус [запрета].</p>
        </header>
    </header>
</content>