<?xml version="1.0" standalone="yes"?>
<content>
    <header level='0' type="chapter" name="7" verbouse_name="Гид аНоше">
        <daf number="960" name="96a">
		</daf>
        <daf number="965" name="96b">
			<mishna>
				<header type='ref' name='hullin_96_yerech_shenitbashel'>
					Бедро, которое сварили, не удалив оттуда гид аНоше, если есть в бедре вкус гид аНоше - оно запрещено.
				</header>
			</mishna>
			<p></p>
			<p></p>
			<p></p>
			<p></p>
			<p></p>
			<p></p>
			<p></p>
        </daf>
    </header>
</content>